TeleGenic/__init__.py
TeleGenic/__main__.py
TeleGenic/base.py
TeleGenic/bot.py
TeleGenic/botcommand.py
TeleGenic/botcommandscope.py
TeleGenic/callbackquery.py
TeleGenic/chat.py
TeleGenic/chataction.py
TeleGenic/chatinvitelink.py
TeleGenic/chatjoinrequest.py
TeleGenic/chatlocation.py
TeleGenic/chatmember.py
TeleGenic/chatmemberupdated.py
TeleGenic/chatpermissions.py
TeleGenic/choseninlineresult.py
TeleGenic/constants.py
TeleGenic/dice.py
TeleGenic/error.py
TeleGenic/forcereply.py
TeleGenic/keyboardbutton.py
TeleGenic/keyboardbuttonpolltype.py
TeleGenic/loginurl.py
TeleGenic/message.py
TeleGenic/messageautodeletetimerchanged.py
TeleGenic/messageentity.py
TeleGenic/messageid.py
TeleGenic/parsemode.py
TeleGenic/poll.py
TeleGenic/proximityalerttriggered.py
TeleGenic/py.typed
TeleGenic/replykeyboardmarkup.py
TeleGenic/replykeyboardremove.py
TeleGenic/replymarkup.py
TeleGenic/update.py
TeleGenic/user.py
TeleGenic/userprofilephotos.py
TeleGenic/version.py
TeleGenic/voicechat.py
TeleGenic/webhookinfo.py
TeleGenic/ext/__init__.py
TeleGenic/ext/basepersistence.py
TeleGenic/ext/callbackcontext.py
TeleGenic/ext/callbackdatacache.py
TeleGenic/ext/callbackqueryhandler.py
TeleGenic/ext/chatjoinrequesthandler.py
TeleGenic/ext/chatmemberhandler.py
TeleGenic/ext/choseninlineresulthandler.py
TeleGenic/ext/commandhandler.py
TeleGenic/ext/contexttypes.py
TeleGenic/ext/conversationhandler.py
TeleGenic/ext/defaults.py
TeleGenic/ext/dictpersistence.py
TeleGenic/ext/dispatcher.py
TeleGenic/ext/extbot.py
TeleGenic/ext/filters.py
TeleGenic/ext/handler.py
TeleGenic/ext/inlinequeryhandler.py
TeleGenic/ext/jobqueue.py
TeleGenic/ext/messagehandler.py
TeleGenic/ext/messagequeue.py
TeleGenic/ext/picklepersistence.py
TeleGenic/ext/pollanswerhandler.py
TeleGenic/ext/pollhandler.py
TeleGenic/ext/precheckoutqueryhandler.py
TeleGenic/ext/regexhandler.py
TeleGenic/ext/shippingqueryhandler.py
TeleGenic/ext/stringcommandhandler.py
TeleGenic/ext/stringregexhandler.py
TeleGenic/ext/typehandler.py
TeleGenic-7.1.dist-info/LICENSE.dual
TeleGenic-7.1.dist-info/METADATA
TeleGenic-7.1.dist-info/WHEEL
TeleGenic-7.1.dist-info/top_level.txt
TeleGenic-7.1.dist-info/RECORD
