Metadata-Version: 2.1
Name: TeleGenic
Version: 7.1
Summary: We have made you a wrapper
Download-URL: https://pypi.org/project/TeleGenic/
Author: BLANK
Author-email: dev.unions@gmail.com
License: LGPLv3
Project-URL: Bug Tracker, https://github.com/Dev-Union/TeleGenic/issues
Project-URL: Source Code, https://github.com/Dev-Union/TeleGenic
Project-URL: News, https://t.me/TheDevsUnion
Keywords: python telegram bot api wrapper
Classifier: Development Status :: 5 - Production/Stable
Classifier: Intended Audience :: Developers
Classifier: License :: OSI Approved :: GNU Lesser General Public License v3 (LGPLv3)
Classifier: Operating System :: OS Independent
Classifier: Topic :: Software Development :: Libraries :: Python Modules
Classifier: Topic :: Communications :: Chat
Classifier: Topic :: Internet
Classifier: Programming Language :: Python
Classifier: Programming Language :: Python :: 3
Classifier: Programming Language :: Python :: 3.6
Classifier: Programming Language :: Python :: 3.7
Classifier: Programming Language :: Python :: 3.8
Classifier: Programming Language :: Python :: 3.9
Requires-Python: >=3.6
License-File: LICENSE.dual
Requires-Dist: certifi
Requires-Dist: tornado >=6.1
Requires-Dist: APScheduler ==3.6.3
Requires-Dist: pytz >=2018.6
Requires-Dist: cachetools ==4.2.2
Requires-Dist: urllib3 ==1.26.13
Provides-Extra: json
Requires-Dist: ujson ; extra == 'json'
Provides-Extra: passport
Requires-Dist: cryptography !=3.4,!=3.4.1,!=3.4.2,!=3.4.3 ; extra == 'passport'
Provides-Extra: socks
Requires-Dist: PySocks ; extra == 'socks'
